{"local":[{"word":"could","sd":"069aa1f5a974ad785ed8304cf9417a07","pho":["kud"],"des":[{"p":"vbl.","d":"can 的过去式"},{"p":"aux.","d":"可以, 能"}],"sen":[{"p":"v.","s":[{"es":"I would go if I <b>could<\/b>.","cs":"能去我就去。"},{"es":"You <b>could<\/b> have been more considerate.","cs":"你本来可以更慎重些。"},{"es":"<b>Could<\/b> you do sth. for me?","cs":"你能替我做件事情吗？"},{"es":"I <b>could<\/b> run faster then.","cs":"我那时能跑得更快一些。"},{"es":"Couldn&#39;t you try it again?","cs":"你可否再试一下？"}]}]}],"netdes":[{"word":"could","des":[{"mf":"could","d":"能","f":429,"tag":"net","s":"但是,当我们在这些情况中使用诸如&quot;可&quot;(might)或&quot;<b>能<\/b>&quot;(<b>could<\/b>)这样的字眼的时候,我们并不是认为,在某人进行决策的时候,他的身上有着一种不同于特定场合因果律所具有的必然影响力的东西在起作用. ","url":"http:\/\/wenku.baidu.com\/view\/48dc5de79b89680203d82540.html"},{"mf":"could","d":"可能","f":69,"tag":"net","s":"从1990年起,林而达多次参加&quot;气候变化框架公约&quot;的谈判,开始意识到气候变化对环境影响的紧迫性,这促使他着手组织一支团队(中国农业科学院农业与气候变化研究中心),开展有关的科学研究,并不断呐喊--如果不阻止气候变化,将来会--不是&quot;<b>可能<\/b>&quot;(<b>could<\/b>)而是&quot;一定&quot;(wi","url":"http:\/\/www.qhdgrain.gov.cn\/article.jsp?id=1229"},{"mf":"could","d":"能够","f":63,"tag":"net","s":"在这种说法中,克里普克同样使用了&quot;关于它&quot;的这个词,&quot;连有人<b>能够<\/b>(<b>could<\/b>)知道关于它(aboutit)的任何先天的事情这个结论,甚至都不能得出&quot;中的&quot;关于它&quot;(aboutit),也不可能是指诸如&quot;假如它为真,则为真就是必然的&quot;等,这是我们先天地熟悉了的;","url":"http:\/\/www.029edu.com\/lunwen\/20080821\/XianTian-8688_10.html"},{"mf":"could","d":"可以","f":18,"tag":"net","s":"不过原文是外交部发言人表示&quot;静观其变&quot;,政府&quot;<b>可以<\/b>&quot;(<b>could<\/b>)提起上诉,没说正在推翻该法令. 因为该法令,得到了98%的国民拥护. 这么高的民意支持度,政府不是想推翻就敢这么做的. ","url":"http:\/\/cache.tianya.cn\/publicforum\/Content\/worldlook\/1\/11041.shtml"}],"wf":"1"},{"word":"Could be","des":[{"mf":"Could be","d":"可能是吧","f":1070,"tag":"net","s":"46 Control yourself! 克制一下! | <b>47 Could be. 可能是吧. <\/b> | 48 Damned fool! 真是笨哦!","url":"http:\/\/www.zk168.com.cn\/INFO\/Study\/FreeThesis\/TeachingThesis\/EnglishTeaching\/14360611215364676040774.html"},{"mf":"Could be","d":"也许","f":356,"tag":"net","s":"Qualified or partial agreement 有保留的或部分赞同 | <b>1. Could be. 也许.<\/b> | 2. If you say so. 既然你这么说.","url":"http:\/\/blog.sina.com.cn\/s\/blog_5cebea0e0100bk53.html"},{"mf":"Could be","d":"可能吧","f":38,"tag":"net","s":"I mean, isn&#39;t that just the height of hypocrisy?|我是说,这难道不是一种伪善的表征 | <b>Could be.|可能吧<\/b> | I don&#39;t hear much helping going on over there.|你好像没在帮什么忙","url":"http:\/\/www.engxue.com\/bencandy.php?aid=746&buy=2&fid=4&line=60.191.233.102&page=3"},{"mf":"Could be","d":"可能是对的","f":33,"tag":"net","s":"Good try, but not quite right.很好的尝试, 但不完全对.  | <b>Could be.可能是对的. <\/b> | It depends.看情况而定. ","url":"http:\/\/www.flshzxyy.com\/showart.asp?id=67&page=42"}]},{"word":"CUD COULD","des":[{"mf":"CUD COULD","d":"能、可(过去式)","f":537,"tag":"net","s":"CUB CUBIC 立方 | <b>CUD COULD 能、可(过去式)<\/b> | CUFT CUBIC FEET 立方英尺","url":"http:\/\/www.wangxiao.cn\/wl\/fudao\/zh\/1028239298.html"},{"mf":"CUD Could","d":"能,可以","f":267,"tag":"net","s":"CTNR Container 集装箱 | <b>CUD Could 能,可以<\/b> | CUN The Charter of the United Nations 联合国宪章","url":"http:\/\/blog.163.com\/xuer_1120\/blog\/static\/6625074200761104120947"},{"mf":"CUD COULD","d":"能","f":20,"tag":"net","s":"CUB CUBIC 立方 | <b>CUD COULD 能<\/b> | CURR;CUR;CURT CURRENT 流通的,现行的","url":"http:\/\/lisazhao1982.spaces.live.com\/blog\/?fl=cat"},{"mf":"CUD COULD","d":"能、可","f":1,"tag":"net","s":"CUB CUBIC 立方 | <b>CUD COULD 能、可<\/b> | CUFT CUBIC FEET 立方英尺","url":"http:\/\/yy.china-b.com\/bec\/beccj\/20090519\/54997_1.html"}]},{"word":"Could I","des":[{"mf":"Could I","d":"我可以用吗","f":370,"tag":"net","s":"so you can drive her home after the party. 在派对结束后送她回家.  | <b>Could I? 我可以用吗?<\/b> | If you drive carefully. 只要你小心驾驶. ","url":"http:\/\/www.qzdd.cn\/stud\/2007\/0922\/article_8563.html"},{"mf":"Could I","d":"我能看一看吗","f":316,"tag":"net","s":"Could she? Could we? 她能看吗?我们能看吗? | <b>Could I? 我能看一看吗?<\/b> | Take them upstairs, Susan. 带他们上楼去,Susan. ","url":"http:\/\/www.tingclass.com\/lesson\/album\/usa\/play315.html"},{"mf":"Could I","d":"请把......给我","f":12,"tag":"net","s":"65. Could you...? 请你......,好吗? | <b>66. Could I...? 请把......给我. <\/b> | 67. Would you...? 请你帮我....... ","url":"http:\/\/www.xinhuabookstore.com\/product\/1318362"},{"mf":"Could I","d":"可以吗","f":6,"tag":"net","s":"You wanna give it a try?|你要不要试一试? | <b>Could I?|可以吗<\/b> | Where the hell is he? I wanna eat.|他到哪去了 我要吃了","url":"http:\/\/www.engxue.com\/bencandy.php?aid=794&buy=2&fid=4&line=&page=2"}]},{"word":"could break","des":[{"mf":"could break","d":"早已破碎","f":309,"tag":"net","s":"find my heart 即使我的心 | <b>could break 早已破碎<\/b> | all over again 深情犹在","url":"http:\/\/fgworld.buluo.tianya.cn\/bulo\/ShowArticle.asp?ArticleID=92643&Key=0&buloid=713&idWriter=0"},{"mf":"could break","d":"再度","f":27,"tag":"net","s":"Find my heart 爱你的心 | <b>Could break 再度<\/b> | All over again 支离破碎","url":"http:\/\/blog.sina.com.cn\/dmlk"},{"mf":"Could break","d":"我的心完全破碎","f":8,"tag":"net","s":"[02:39.57]Something that time just can&#39;t erase 还有那些时光不能摸去的记忆! | <b>[02:46.07]Could break 我的心完全破碎,<\/b> | [02:48.04]All over again 拥有的一切再一次失去!","url":"http:\/\/www.ailrc.com\/SZXSOZP.html"},{"mf":"Could break","d":"不断崩溃着","f":7,"tag":"net","s":"Something that time just can&#39;t erase 一些时间无法磨灭的东西 | Find my heart 正抓住我的心 | <b>Could break 不断崩溃着<\/b>","url":"http:\/\/iceobebe.spaces.live.com\/blog\/"}]},{"word":"could go","des":[{"mf":"could go","d":"巴不得吃(或喝)","f":331,"tag":"net","s":"earthfast 牢固在土中的 | <b>could go 巴不得吃(或喝)<\/b> | abed 在床上, 卧病在床","url":"http:\/\/topic.xtsz.com.cn\/archive\/4a7a1375501be.html"}]}],"netsen":[{"cs":"我是你的唯一。。。","es":"I <b>could<\/b> be the one ...","url":"http:\/\/bbs.hongxiu.com\/view.asp?BID=29&TITLE=%CE%D2%BA%CD%B0%CB%B8%E7%B5%C4%B5%E3%B5%E3%CD%F9%CA%C2%A3%A8%CD%EA%A3%A9&bname=%BA%EC%D0%E4%BC%D1%C8%CB&id=1068537&pagenum=39&tables=A&ztables=assi"},{"cs":"我会的，你知道。","es":"I <b>could<\/b> do it,you know.","url":"http:\/\/www.gdcy52.org\/article\/1879\/114091"},{"cs":"我是说，你知道吗，你可以做的","es":"I mean, you know, you <b>could<\/b> do it.","url":"http:\/\/engxue.com\/bencandy.php?aid=218&fid=6&page=2"},{"cs":"我希望我能告诉你，但。。。","es":"I wish I <b>could<\/b> help you, but...","url":"http:\/\/www.icoolen.com\/film_veido\/desperate_season5_chapter16"},{"cs":"我能，我能做。。。","es":"I <b>could<\/b>, I <b>could<\/b> do...","url":"http:\/\/lexdex.com\/film_veido\/friends_chapter7_8"},{"cs":"我不知道我能做些什么？","es":"I don&#39;t know what I <b>could<\/b> have done.","url":"http:\/\/bbs.gao00.com\/viewthread.php?tid=39340"},{"cs":"我以为我能过的很好。。。。","es":"I thought I <b>could<\/b> have been very good....","url":"http:\/\/www.ahmoi.com\/action\/blog\/one.php?id=49661ae73595c"}],"dlg":[{"s":"\/职场英语","t":"传递信息","c":[{"n":"A","cs":"你可以把这个（口讯\/报告\/文件）给他吗？","es":"<b>Could<\/b> you give him this (message\/ report\/ document), please?"},{"n":"B","cs":"没问题。","es":"No problem."}],"u":0},{"s":"\/衣食住行","t":"还礼","c":[{"n":"A","cs":"你帮我大忙了。","es":"You’ve been a big help."},{"n":"B","cs":"能帮助您，我非常高兴。","es":"I’m glad I <b>could<\/b> help."}],"u":1},{"s":"\/衣食住行","t":"请求帮助","c":[{"n":"A","cs":"您能把盐递过来吗?","es":"<b>Could<\/b> you hand me the salt, please?"},{"n":"B","cs":"乐意为您效劳。","es":"With pleasure. Here you are."}],"u":0}],"lang": "eng"}
